setup.cfg
setup.py
scrapy_venom/__init__.py
scrapy_venom/exceptions.py
scrapy_venom/spiders.py
scrapy_venom/steps.py
scrapy_venom/utils.py
scrapy_venom.egg-info/PKG-INFO
scrapy_venom.egg-info/SOURCES.txt
scrapy_venom.egg-info/dependency_links.txt
scrapy_venom.egg-info/entry_points.txt
scrapy_venom.egg-info/not-zip-safe
scrapy_venom.egg-info/requires.txt
scrapy_venom.egg-info/top_level.txt
scrapy_venom/steps/__init__.py
scrapy_venom/steps/base.py
scrapy_venom/steps/generics.py
scrapy_venom/steps/mixins.py