Metadata-Version: 1.1
Name: scrapy-venom
Version: 0.1.1
Summary: Generic classes to deal with data scraping using Scrapy
Home-page: https://github.com/intelivix/scrapy-venom
Author: Tiago Lira
Author-email: tiago@intelivix.com
License: UNKNOWN
Download-URL: https://github.com/intelivix/scrapy-venom/tarball/0.1
Keywords: scrapy,scraping,steps,flows
Platform: UNKNOWN
